sequenceutils/__about__.py
sequenceutils/__init__.py
sequenceutils/computed_sequence.py
sequenceutils/concatenated_sequence.py
sequenceutils-0.1.1.dist-info/METADATA
sequenceutils-0.1.1.dist-info/WHEEL
sequenceutils-0.1.1.dist-info/licenses/LICENSE
sequenceutils-0.1.1.dist-info/RECORD
