Metadata-Version: 2.4
Name: sequenceutils
Version: 0.1.1
Project-URL: Documentation, https://github.com/brandjas/sequenceutils#readme
Project-URL: Issues, https://github.com/brandjas/sequenceutils/issues
Project-URL: Source, https://github.com/brandjas/sequenceutils
Author-email: brandjas <brandjas@users.noreply.github.com>
License-Expression: MIT
License-File: LICENSE
Classifier: Development Status :: 4 - Beta
Classifier: Programming Language :: Python
Classifier: Programming Language :: Python :: 3.10
Classifier: Programming Language :: Python :: 3.11
Classifier: Programming Language :: Python :: 3.12
Classifier: Programming Language :: Python :: 3.13
Classifier: Programming Language :: Python :: 3.14
Classifier: Programming Language :: Python :: Implementation :: CPython
Requires-Python: >=3.10
